seutil/BashUtils.py
seutil/CliUtils.py
seutil/GitHubUtils.py
seutil/LoggingUtils.py
seutil/MiscUtils.py
seutil/Stream.py
seutil/TimeUtils.py
seutil/__init__.py
seutil/arg.py
seutil/bash.py
seutil/ds/__init__.py
seutil/ds/graph_common.py
seutil/ds/lattice.py
seutil/ds/trie.py
seutil/io.py
seutil/latex.py
seutil/latex_old/File.py
seutil/latex_old/Macro.py
seutil/latex_old/Table.py
seutil/latex_old/__init__.py
seutil/log.py
seutil/maven.py
seutil/pbar.py
seutil/powershell.py
seutil/project.py
seutil-0.9.0.dist-info/WHEEL
seutil-0.9.0.dist-info/METADATA
seutil-0.9.0.dist-info/RECORD
