Metadata-Version: 2.3
Name: seutil
Version: 0.9.0
Summary: Python utilities for SE research
Author: Pengyu Nie
Author-email: Pengyu Nie <prodigy.sov@gmail.com>
License:                                  Apache License
Classifier: Topic :: Utilities
Classifier: Programming Language :: Python :: 3.9
Classifier: Programming Language :: Python :: 3.10
Classifier: Programming Language :: Python :: 3.11
Classifier: Programming Language :: Python :: 3.12
Classifier: Programming Language :: Python :: 3.13
Classifier: Programming Language :: Python :: 3.14
Classifier: License :: OSI Approved :: Apache Software License
Classifier: Operating System :: POSIX :: Linux
Requires-Dist: ijson~=3.1.4
Requires-Dist: igraph>=0.9.10
Requires-Dist: jsonargparse[signatures]>=4.1.4
Requires-Dist: lazy-import>=0.2.2
Requires-Dist: numpy>=1.14.4
Requires-Dist: pygithub>=1.40
Requires-Dist: pyyaml>=5.1
Requires-Dist: tqdm>=4.62.3
Requires-Dist: typing-inspect>=0.4.0
Requires-Dist: unidiff>=0.5.5
Requires-Dist: xmltodict>=0.2.2
Requires-Python: >=3.9
Project-URL: Documentation, https://seutil.readthedocs.io/en/latest/
Project-URL: Issues, https://github.com/pengyunie/seutil/issues
Project-URL: Source, https://github.com/pengyunie/seutil
